figleaf_fasta/__init__.py
figleaf_fasta/figleaf.py
figleaf_fasta/utils.py
figleaf_fasta-1.1.1.dist-info/AUTHORS.md
figleaf_fasta-1.1.1.dist-info/LICENSE
figleaf_fasta-1.1.1.dist-info/METADATA
figleaf_fasta-1.1.1.dist-info/WHEEL
figleaf_fasta-1.1.1.dist-info/entry_points.txt
figleaf_fasta-1.1.1.dist-info/top_level.txt
figleaf_fasta-1.1.1.dist-info/RECORD
