Metadata-Version: 2.1
Name: figleaf-fasta
Version: 1.1.1
Summary: figleaf_fasta applies hard/soft masking to a FASTA file or excludes/extracts sub-sequences from a FASTA file.
Home-page: https://github.com/AlexOrlek/figleaf_fasta
Author: Alex Orlek
Author-email: alex.orlek@gmail.com
License: MIT license
Keywords: figleaf_fasta
Platform: UNKNOWN
Classifier: Development Status :: 3 - Alpha
Classifier: Intended Audience :: Science/Research
Classifier: License :: OSI Approved :: MIT License
Classifier: Natural Language :: English
Classifier: Programming Language :: Python :: 3
Classifier: Programming Language :: Python :: 3.6
Classifier: Programming Language :: Python :: 3.7
Classifier: Programming Language :: Python :: 3.8
Classifier: Programming Language :: Python :: 3.9
Requires-Python: >=3.6
Requires-Dist: biopython (>=1.61)
